docs2db/__init__.py
docs2db/audit.py
docs2db/chunks.py
docs2db/config.py
docs2db/const.py
docs2db/database.py
docs2db/db_lifecycle.py
docs2db/docs2db.py
docs2db/embed.py
docs2db/embeddings.py
docs2db/exceptions.py
docs2db/ingest.py
docs2db/multiproc.py
docs2db/utils.py
docs2db-0.4.3.dist-info/WHEEL
docs2db-0.4.3.dist-info/entry_points.txt
docs2db-0.4.3.dist-info/METADATA
docs2db-0.4.3.dist-info/RECORD
