Metadata-Version: 2.3
Name: docs2db
Version: 0.4.3
Summary: Repository of docling documents for RAG
Keywords: rag,document-processing,embeddings,docling,contextual-retrieval,semantic-search,vector-database,pgvector,postgresql,llm
Author: Ellis Low
Author-email: Ellis Low <elow@redhat.com>
License: Apache-2.0
Classifier: Development Status :: 4 - Beta
Classifier: Intended Audience :: Developers
Classifier: License :: OSI Approved :: Apache Software License
Classifier: Programming Language :: Python :: 3
Classifier: Programming Language :: Python :: 3.12
Classifier: Topic :: Scientific/Engineering :: Artificial Intelligence
Classifier: Topic :: Software Development :: Libraries :: Python Modules
Classifier: Topic :: Text Processing :: General
Requires-Dist: cachetools>=6.1.0
Requires-Dist: docling>=2.42.1
Requires-Dist: httpx>=0.28.1
Requires-Dist: pgvector>=0.3.8
Requires-Dist: psycopg[binary]>=3.2.3
Requires-Dist: psycopg-pool>=3.2.6
Requires-Dist: pydantic-settings>=2.10.1
Requires-Dist: pyyaml>=6.0.1
Requires-Dist: rich>=14.0.0
Requires-Dist: structlog>=25.4.0
Requires-Dist: torch>=2.7.1
Requires-Dist: tqdm>=4.67.1
Requires-Dist: xxhash>=3.5.0
Requires-Dist: ibm-watsonx-ai>=1.3.32 ; extra == 'watsonx'
Requires-Python: >=3.12, <3.13
Project-URL: Changelog, https://github.com/rhel-lightspeed/docs2db/blob/main/CHANGELOG.md
Project-URL: Documentation, https://github.com/rhel-lightspeed/docs2db#readme
Project-URL: Homepage, https://github.com/rhel-lightspeed/docs2db
Project-URL: Issues, https://github.com/rhel-lightspeed/docs2db/issues
Project-URL: Repository, https://github.com/rhel-lightspeed/docs2db
Provides-Extra: watsonx
